djangophone/manage.py
djangophone/core/__init__.py
djangophone/core/admin.py
djangophone/core/apps.py
djangophone/core/fields.py
djangophone/core/forms.py
djangophone/core/models.py
djangophone/core/py.typed
djangophone/core/serializers.py
djangophone/core/tests.py
djangophone/core/utils.py
djangophone/core/validators.py
djangophone/core/views.py
djangophone/core/migrations/__init__.py
djangophone/djangophone/__init__.py
djangophone/djangophone/asgi.py
djangophone/djangophone/settings.py
djangophone/djangophone/urls.py
djangophone/djangophone/wsgi.py
tests/settings.py
tests/test_fields.py
tests/test_serializer.py
phonenumberfield_lite-0.1.0.dist-info/METADATA
phonenumberfield_lite-0.1.0.dist-info/WHEEL
phonenumberfield_lite-0.1.0.dist-info/top_level.txt
phonenumberfield_lite-0.1.0.dist-info/RECORD
