Metadata-Version: 2.4
Name: phonenumberfield_lite
Version: 0.1.0
Summary: Lightweight phone number field for Django
Author-email: Amirhoseinheidari <amirhosein.hydri1381@email.com>
Requires-Dist: Django>=3.2
Requires-Dist: phonenumbers>=8.13
